coconerd/__init__.py
coconerd/main.py
coconerd-0.3.data/scripts/coconerd
tests/__init__.py
tests/test.py
coconerd-0.3.dist-info/LICENSE
coconerd-0.3.dist-info/METADATA
coconerd-0.3.dist-info/WHEEL
coconerd-0.3.dist-info/top_level.txt
coconerd-0.3.dist-info/RECORD
