Metadata-Version: 2.1
Name: coconerd
Version: 0.3
Summary: Code counts for Nerd (a.k.a doctoral student in computer science)
Home-page: https://github.com/trungnt13/Code-counts
Author: Trung Ngo
Author-email: anonymouswork90@gmail.com
License: MIT license
Keywords: coconerd
Platform: UNKNOWN
Classifier: Development Status :: 4 - Beta
Classifier: License :: OSI Approved :: MIT License
Classifier: Natural Language :: English
Classifier: Programming Language :: Python :: 3.7
Classifier: Operating System :: MacOS :: MacOS X
Classifier: Operating System :: Microsoft :: Windows
Classifier: Operating System :: POSIX :: Linux
Classifier: Intended Audience :: Developers
Classifier: Intended Audience :: Education
Classifier: Intended Audience :: Science/Research
Requires-Dist: tqdm (>=4.61.2)
